polybugger_mcp/__init__.py
polybugger_mcp/adapters/__init__.py
polybugger_mcp/adapters/base.py
polybugger_mcp/adapters/codelldb_adapter.py
polybugger_mcp/adapters/dap_client.py
polybugger_mcp/adapters/debugpy_adapter.py
polybugger_mcp/adapters/delve_adapter.py
polybugger_mcp/adapters/factory.py
polybugger_mcp/adapters/node_adapter.py
polybugger_mcp/api/__init__.py
polybugger_mcp/api/breakpoints.py
polybugger_mcp/api/deps.py
polybugger_mcp/api/errors.py
polybugger_mcp/api/execution.py
polybugger_mcp/api/inspection.py
polybugger_mcp/api/output.py
polybugger_mcp/api/recovery.py
polybugger_mcp/api/router.py
polybugger_mcp/api/server.py
polybugger_mcp/api/sessions.py
polybugger_mcp/api/watches.py
polybugger_mcp/config.py
polybugger_mcp/containers/__init__.py
polybugger_mcp/containers/base.py
polybugger_mcp/containers/docker.py
polybugger_mcp/containers/factory.py
polybugger_mcp/containers/kubernetes.py
polybugger_mcp/containers/models.py
polybugger_mcp/containers/podman.py
polybugger_mcp/containers/ssh_tunnel.py
polybugger_mcp/core/__init__.py
polybugger_mcp/core/events.py
polybugger_mcp/core/exceptions.py
polybugger_mcp/core/session.py
polybugger_mcp/main.py
polybugger_mcp/mcp_server.py
polybugger_mcp/models/__init__.py
polybugger_mcp/models/container.py
polybugger_mcp/models/dap.py
polybugger_mcp/models/events.py
polybugger_mcp/models/inspection.py
polybugger_mcp/models/requests.py
polybugger_mcp/models/responses.py
polybugger_mcp/models/session.py
polybugger_mcp/persistence/__init__.py
polybugger_mcp/persistence/breakpoints.py
polybugger_mcp/persistence/sessions.py
polybugger_mcp/persistence/storage.py
polybugger_mcp/utils/__init__.py
polybugger_mcp/utils/data_inspector.py
polybugger_mcp/utils/output_buffer.py
polybugger_mcp/utils/source_reader.py
polybugger_mcp/utils/tui_formatter.py
polybugger_mcp-1.8.0.dist-info/METADATA
polybugger_mcp-1.8.0.dist-info/WHEEL
polybugger_mcp-1.8.0.dist-info/entry_points.txt
polybugger_mcp-1.8.0.dist-info/licenses/LICENSE
polybugger_mcp-1.8.0.dist-info/RECORD
