Metadata-Version: 2.4
Name: polybugger-mcp
Version: 1.8.0
Summary: MCP server for multi-language debugging with AI agents via DAP (Python, Go, Rust, Node.js)
License: MIT
License-File: LICENSE
Keywords: mcp,debugger,debugging,ai,dap,debugpy,delve,lldb,python,go,rust,model-context-protocol
Author: Amir Wilf
Requires-Python: >=3.10,<4.0
Classifier: Development Status :: 3 - Alpha
Classifier: Framework :: FastAPI
Classifier: Intended Audience :: Developers
Classifier: License :: OSI Approved :: MIT License
Classifier: Programming Language :: Python :: 3
Classifier: Programming Language :: Python :: 3.10
Classifier: Programming Language :: Python :: 3.11
Classifier: Programming Language :: Python :: 3.12
Classifier: Programming Language :: Python :: 3.13
Classifier: Programming Language :: Python :: 3.14
Classifier: Topic :: Software Development :: Debuggers
Classifier: Topic :: Software Development :: Testing
Requires-Dist: aiofiles (>=23.2.0)
Requires-Dist: debugpy (>=1.8.0)
Requires-Dist: fastapi (>=0.109.0)
Requires-Dist: mcp (>=1.0.0)
Requires-Dist: pydantic (>=2.5.0)
Requires-Dist: pydantic-settings (>=2.1.0)
Requires-Dist: uvicorn[standard] (>=0.27.0)
Project-URL: Changelog, https://github.com/wilfoa/polybugger-mcp/blob/main/CHANGELOG.md
Project-URL: Documentation, https://github.com/wilfoa/polybugger-mcp#readme
Project-URL: Homepage, https://github.com/wilfoa/polybugger-mcp
Project-URL: Issues, https://github.com/wilfoa/polybugger-mcp/issues
Project-URL: Repository, https://github.com/wilfoa/polybugger-mcp
